tests/__init__.py
tests/test_exps.py
tests/test_folders.py
tests/test_session.py
traxer/__init__.py
traxer/client/__init__.py
traxer/client/client.py
traxer/client/experiment.py
traxer/client/session.py
traxer/server/__init__.py
traxer/server/models.py
traxer/server/run_server.py
traxer/server/search.py
traxer/server/utils.py
traxer/server/wsgi.py
traxer/server/frontend/build/asset-manifest.json
traxer/server/frontend/build/favicon.ico
traxer/server/frontend/build/general.css
traxer/server/frontend/build/index.html
traxer/server/frontend/build/index.html.save
traxer/server/frontend/build/manifest.json
traxer/server/frontend/build/precache-manifest.64d96bd9537d2f47b99cef9512a95819.js
traxer/server/frontend/build/robots.txt
traxer/server/frontend/build/service-worker.js
traxer/server/frontend/build/static/css/2.c22a4aeb.chunk.css
traxer/server/frontend/build/static/css/2.c22a4aeb.chunk.css.map
traxer/server/frontend/build/static/css/main.be9cd952.chunk.css
traxer/server/frontend/build/static/css/main.be9cd952.chunk.css.map
traxer/server/frontend/build/static/js/2.fc365d2a.chunk.js
traxer/server/frontend/build/static/js/2.fc365d2a.chunk.js.map
traxer/server/frontend/build/static/js/3.92e190a6.chunk.js
traxer/server/frontend/build/static/js/3.92e190a6.chunk.js.map
traxer/server/frontend/build/static/js/main.87837ddb.chunk.js
traxer/server/frontend/build/static/js/main.87837ddb.chunk.js.map
traxer/server/frontend/build/static/js/runtime~main.2a686703.js
traxer/server/frontend/build/static/js/runtime~main.2a686703.js.map
traxer/server/frontend/public/favicon.ico
traxer/server/frontend/public/general.css
traxer/server/frontend/public/index.html
traxer/server/frontend/public/index.html.save
traxer/server/frontend/public/manifest.json
traxer/server/frontend/public/robots.txt
traxer/utils/__init__.py
traxer/utils/process.py
Traxer-0.2.0.dist-info/LICENSE
Traxer-0.2.0.dist-info/METADATA
Traxer-0.2.0.dist-info/WHEEL
Traxer-0.2.0.dist-info/entry_points.txt
Traxer-0.2.0.dist-info/top_level.txt
Traxer-0.2.0.dist-info/RECORD
