Metadata-Version: 2.1
Name: Traxer
Version: 0.2.0
Summary: Track and visualize your experiments
Home-page: UNKNOWN
Author: Jules Tevissen
License: MIT
Platform: UNKNOWN
Classifier: Programming Language :: Python :: 3
Classifier: Programming Language :: Python :: 3.6
Classifier: Programming Language :: Python :: 3.7
Classifier: Programming Language :: Python :: 3.8
Classifier: Programming Language :: Python :: 3.9
Classifier: Programming Language :: Python :: 3.10
Requires-Python: >=3.6
Requires-Dist: numpy
Requires-Dist: bokeh
Requires-Dist: mongoengine
Requires-Dist: Flask
Requires-Dist: flask-cors
Requires-Dist: pyyaml
Requires-Dist: click
Requires-Dist: gunicorn
Requires-Dist: psutil
